aisp/__init__.py
aisp/exceptions.py
aisp/base/__init__.py
aisp/base/core/__init__.py
aisp/base/core/_base.py
aisp/base/core/_classifier.py
aisp/base/core/_clusterer.py
aisp/base/core/_optimizer.py
aisp/base/immune/__init__.py
aisp/base/immune/cell.py
aisp/base/immune/mutation.py
aisp/base/immune/populations.py
aisp/csa/__init__.py
aisp/csa/_ai_recognition_sys.py
aisp/csa/_clonalg.py
aisp/ina/__init__.py
aisp/ina/_ai_network.py
aisp/nsa/__init__.py
aisp/nsa/_base.py
aisp/nsa/_binary_negative_selection.py
aisp/nsa/_negative_selection.py
aisp/utils/__init__.py
aisp/utils/display.py
aisp/utils/distance.py
aisp/utils/metrics.py
aisp/utils/multiclass.py
aisp/utils/random.py
aisp/utils/sanitizers.py
aisp/utils/types.py
aisp/utils/validation.py
aisp-0.5.1.dist-info/licenses/LICENSE
aisp-0.5.1.dist-info/METADATA
aisp-0.5.1.dist-info/WHEEL
aisp-0.5.1.dist-info/top_level.txt
aisp-0.5.1.dist-info/RECORD
