Metadata-Version: 2.4
Name: aisp
Version: 0.5.1
Summary: Package with techniques of artificial immune systems.
Author-email: João Paulo da Silva Barros <jpsilvabarr@gmail.com>
Maintainer-email: Alison Zille Lopes <alisonzille@gmail.com>
License-Expression: LGPL-3.0-only
Project-URL: Homepage, https://ais-package.github.io/
Project-URL: Documentation, https://ais-package.github.io/docs/intro
Project-URL: Source Code, https://github.com/AIS-Package/aisp
Project-URL: Tracker, https://github.com/AIS-Package/aisp/issues
Keywords: Artificial Immune Systems,classification,Natural computing,machine learning,artificial intelligence,AIS
Classifier: Operating System :: OS Independent
Classifier: Programming Language :: Python
Classifier: Programming Language :: Python :: 3
Classifier: Programming Language :: Python :: 3.10
Classifier: Programming Language :: Python :: 3.11
Classifier: Programming Language :: Python :: 3.12
Classifier: Programming Language :: Python :: 3.13
Classifier: Topic :: Scientific/Engineering :: Artificial Intelligence
Classifier: Topic :: Software Development :: Libraries :: Python Modules
Requires-Python: >=3.10
License-File: LICENSE
Requires-Dist: numpy>=1.22.4
Requires-Dist: numba>=0.59.0
Requires-Dist: scipy>=1.8.1
Requires-Dist: tqdm>=4.64.1
Provides-Extra: dev
Requires-Dist: build>=1.2.2.post1; extra == "dev"
Requires-Dist: ipykernel>=6.29.5; extra == "dev"
Requires-Dist: twine>=5.1.1; extra == "dev"
Requires-Dist: pytest>=8.3.5; extra == "dev"
Dynamic: license-file
